{
  "user": [
    {
      "username": "abc",
      "nickname": "에이비씨",
      "password": "password",
      "confirmPassword": "password",
      "id": 1
    },
    {
      "username": "test",
      "nickname": "닉네임",
      "password": "qlalfqjsgh",
      "confirmPassword": "qlalfqjsgh",
      "id": 2
    },
    {
      "username": "test22",
      "nickname": "테스뚜",
      "password": "qlalfqjsgh",
      "confirmPassword": "qlalfqjsgh",
      "id": 3
    },
    {
      "username": "test123",
      "nickname": "테스트입니다",
      "password": "xptmxm",
      "confirmPassword": "xptmxm",
      "id": 4
    },
    {
      "username": "test1234",
      "nickname": "테스트에요",
      "password": "xptmxm",
      "confirmPassword": "xptmxm",
      "id": 5
    },
    {
      "username": "testtest22",
      "nickname": "테스트닉네임",
      "password": "qlalfqjsgh",
      "confirmPassword": "qlalfqjsgh",
      "id": 6
    }
  ],
  "posts": [
    {
      "id": 1,
      "title": "공동구매합니다",
      "category": "PURCHASE",
      "deadline": "2022.07.23",
      "numberPeople": 4,
      "currentNumberPeople": 1,
      "contactMethod": "email",
      "viewCount": 3,
      "commentCount": 0,
      "nickname": "test",
      "imageUrl": "https://velog.velcdn.com/images/kimhyo_0218/post/cdab776f-8cdf-4fd0-9e9f-5f59ad8d5b69/reactquery_logo.png",
      "content": "공구할사람 손들어라~",
      "createdAt": "2022.07.17"
    },
    {
      "id": 2,
      "title": "공연 같이 보실분",
      "category": "EXHIBITION",
      "deadline": "2022.07.25",
      "numberPeople": 3,
      "currentNumberPeople": 2,
      "contactMethod": "오픈카톡방",
      "viewCount": 1,
      "commentCount": 0,
      "nickname": "testtest",
      "imageUrl": "https://images.velog.io/images/cyheum/post/37534693-2ae7-4134-91ab-af7eb74b7efb/react-logo.png",
      "content": "멜로망스..... 영접하고시퍼요",
      "createdAt": "2022.07.22"
    },
    {
      "title": "심심한사람 전시회같이가요",
      "category": "EXHIBITION",
      "deadline": "2022.07.27",
      "numberPeople": 2,
      "currentNumberPeople": 1,
      "contactMethod": "오픈카톡방",
      "viewCount": 5,
      "commentCount": 1,
      "nickname": "백수",
      "imageUrl": "https://blog.kakaocdn.net/dn/bLLREg/btrbhYLdx4M/w3BWXIjm185YfkGITrU9HK/img.jpg",
      "id": 3,
      "content": "전시회 함께하실 분~ 오픈카톡방으로 오세요",
      "createdAt": "2022.07.23"
    }
  ],
  "comment": [
    {
      "content": "성별이 어떻게 되세요?",
      "nickname": "호이호이",
      "createdAt": "2022.07.23",
      "postId": "3",
      "id": 1
    },
    {
      "content": "몇시에 모이나요?",
      "nickname": "전시회전국일주",
      "createdAt": "2022.07.22",
      "postId": "3",
      "id": 2
    },
    {
      "content": "저도 살래요",
      "nickname": "미니멀리즘",
      "createdAt": "2022.07.21",
      "postId": "1",
      "id": 3
    },
    {
      "content": "테스트 댓글",
      "createdAt": "2022.7.25",
      "postId": "3",
      "nickname": "테스트닉네임",
      "id": 4
    }
  ]
}